tasha.py
tasha-0.0.0.dist-info/LICENSE
tasha-0.0.0.dist-info/METADATA
tasha-0.0.0.dist-info/WHEEL
tasha-0.0.0.dist-info/top_level.txt
tasha-0.0.0.dist-info/RECORD
