Metadata-Version: 2.1
Name: tasha
Version: 0.0.0
Summary: Collection of various programs, scripts and libraries I created for personal use (mostly just for fun), gathered in one package for easier management. **WARNING: THIS CODE IS NOT USABLE YET!** 
Author-email: Paweł Ścierski <escer@protonmail.ch>
License: MIT License
Keywords: ai,chatgpt,fortune,fun,scripting
Classifier: Development Status :: 1 - Planning
Classifier: Environment :: Console
Classifier: Intended Audience :: Developers
Classifier: Intended Audience :: Education
Classifier: Intended Audience :: Science/Research
Classifier: License :: OSI Approved :: MIT License
Classifier: Operating System :: OS Independent
Classifier: Programming Language :: Python
Classifier: Programming Language :: Python :: 3 :: Only
Classifier: Programming Language :: Python :: 3.12
Classifier: Topic :: Games/Entertainment
Classifier: Topic :: Scientific/Engineering :: Artificial Intelligence
Classifier: Topic :: Text Processing
Classifier: Topic :: Utilities
Requires-Python: >=3.12
License-File: LICENSE
